kevinbotlib_deploytool/__about__.py
kevinbotlib_deploytool/__init__.py
kevinbotlib_deploytool/deployfile.py
kevinbotlib_deploytool/service.py
kevinbotlib_deploytool/sshkeys.py
kevinbotlib_deploytool/cli/__init__.py
kevinbotlib_deploytool/cli/common.py
kevinbotlib_deploytool/cli/deploy_code.py
kevinbotlib_deploytool/cli/init.py
kevinbotlib_deploytool/cli/robot.py
kevinbotlib_deploytool/cli/robot_delete.py
kevinbotlib_deploytool/cli/robot_service.py
kevinbotlib_deploytool/cli/spinner.py
kevinbotlib_deploytool/cli/ssh.py
kevinbotlib_deploytool/cli/ssh_apply_key.py
kevinbotlib_deploytool/cli/test.py
kevinbotlib_deploytool/cli/venv.py
kevinbotlib_deploytool/cli/venv_create.py
kevinbotlib_deploytool/cli/venv_delete.py
kevinbotlib_deploytool-0.0.1a3.dist-info/METADATA
kevinbotlib_deploytool-0.0.1a3.dist-info/WHEEL
kevinbotlib_deploytool-0.0.1a3.dist-info/entry_points.txt
kevinbotlib_deploytool-0.0.1a3.dist-info/licenses/LICENSE
kevinbotlib_deploytool-0.0.1a3.dist-info/RECORD
